{
  "versionCode": 28,
  "versionName": "4.0",
  "downloadUrl": "https://github.com/BwillV/Aunload/releases/download/v4.0/AUnloadRescue-4.0.apk",
  "updateRequired": false,
  "message": "🎉 Actualización 4.0\n\n• Cada container ahora muestra la HORA DE INICIO y FIN (primer y último receiving/put away) en letra grande, justo debajo de Active. Incluye la opción «Excluir a:» para que el trabajo de una persona no cuente en ese cálculo.\n\n• Dentro de cada SKU puedes activar «Mostrar pallets × cantidad» (menú de los tres puntitos ⋮).\n\n• Si en receiving se puso una cantidad de cajas y luego se corrige en put away, ahora SIEMPRE vale la última (la corregida).\n\n⚠️ IMPORTANTE: después de actualizar tienes que volver a activar el botón flotante. Primero DESACTÍVALO y luego ACTÍVALO. Al abrir la app te saldrá un recuadro con un botón para hacerlo directo."
}
